sr_agreement/__init__.py
sr_agreement/superranker.py
sr_agreement-0.0.12.dist-info/METADATA
sr_agreement-0.0.12.dist-info/WHEEL
sr_agreement-0.0.12.dist-info/RECORD
